fennol/__init__.py
fennol/analyze.py
fennol/ase.py
fennol/version.py
fennol/md/__init__.py
fennol/md/barostats.py
fennol/md/colvars.py
fennol/md/dynamic.py
fennol/md/initial.py
fennol/md/integrate.py
fennol/md/spectra.py
fennol/md/thermostats.py
fennol/md/utils.py
fennol/models/__init__.py
fennol/models/fennix.py
fennol/models/inspect.py
fennol/models/modules.py
fennol/models/preprocessing.py
fennol/models/embeddings/__init__.py
fennol/models/embeddings/aimnet.py
fennol/models/embeddings/allegro.py
fennol/models/embeddings/ani.py
fennol/models/embeddings/caiman.py
fennol/models/embeddings/charge_embeddings.py
fennol/models/embeddings/chgnet.py
fennol/models/embeddings/crate.py
fennol/models/embeddings/deeppot.py
fennol/models/embeddings/eeacsf.py
fennol/models/embeddings/foam.py
fennol/models/embeddings/gaussian_moments.py
fennol/models/embeddings/hipnn.py
fennol/models/embeddings/mace.py
fennol/models/embeddings/minimace.py
fennol/models/embeddings/newtonnet.py
fennol/models/embeddings/painn.py
fennol/models/embeddings/raster.py
fennol/models/embeddings/schnet.py
fennol/models/embeddings/spookynet.py
fennol/models/misc/__init__.py
fennol/models/misc/e3.py
fennol/models/misc/encodings.py
fennol/models/misc/misc.py
fennol/models/misc/nets.py
fennol/models/misc/uncertainty.py
fennol/models/physics/__init__.py
fennol/models/physics/bond.py
fennol/models/physics/dispersion.py
fennol/models/physics/electric_field.py
fennol/models/physics/electrostatics.py
fennol/models/physics/nlh_coeffs.dat
fennol/models/physics/polarisation.py
fennol/models/physics/ref_data_d3.pkl
fennol/models/physics/repulsion.py
fennol/training/__init__.py
fennol/training/databases.py
fennol/training/io.py
fennol/training/optimizers.py
fennol/training/training.py
fennol/training/utils.py
fennol/utils/__init__.py
fennol/utils/activations.py
fennol/utils/atomic_units.py
fennol/utils/deconvolution.py
fennol/utils/initializers.py
fennol/utils/input_parser.py
fennol/utils/io.py
fennol/utils/kspace.py
fennol-2025.12.12.post1.dist-info/licenses/LICENSE
fennol-2025.12.12.post1.dist-info/METADATA
fennol-2025.12.12.post1.dist-info/WHEEL
fennol-2025.12.12.post1.dist-info/entry_points.txt
fennol-2025.12.12.post1.dist-info/top_level.txt
fennol-2025.12.12.post1.dist-info/RECORD
