Metadata-Version: 2.4
Name: FeNNol
Version: 2025.12.12.post1
Summary: FeNNol: Force-field-enhanced Neural Network optimized library
Author-email: Thomas Plé <thomas.ple@sorbonne-universite.fr>
Project-URL: Homepage, https://github.com/FeNNol-tools/FeNNol
Keywords: machine learning potential,jax,force field,molecular dynamics
Classifier: Programming Language :: Python
Classifier: Programming Language :: Python :: 3
Classifier: Topic :: Scientific/Engineering :: Chemistry
Classifier: Topic :: Scientific/Engineering :: Artificial Intelligence
License-File: LICENSE
Requires-Dist: jax
Requires-Dist: numpy
Requires-Dist: numba
Requires-Dist: h5py
Requires-Dist: scipy
Requires-Dist: sympy
Requires-Dist: flax[all]
Requires-Dist: tomlkit
Requires-Dist: optax
Requires-Dist: ase
Requires-Dist: pytest
Provides-Extra: cuda
Requires-Dist: jax[cuda12]; extra == "cuda"
Provides-Extra: e3nn
Requires-Dist: e3nn-jax; extra == "e3nn"
Provides-Extra: deephp
Requires-Dist: cffi; extra == "deephp"
Requires-Dist: pydlpack; extra == "deephp"
Requires-Dist: pycuda; extra == "deephp"
Dynamic: license-file
